Metadata-Version: 2.1
Name: sentry-dingding-lz
Version: 1.0.3
Summary: A Sentry extension which send errors stats to DingDing
Home-page: https://github.com/leonzhang2008/sentry-dingding.git
Author: leonzhang
Author-email: leonzhang2008@gmail.com
License: MIT
Keywords: sentry dingding
Platform: UNKNOWN
Classifier: Programming Language :: Python :: 2.7
Classifier: License :: OSI Approved :: MIT License
Requires-Dist: sentry (>=9.0.0)
Requires-Dist: requests
